liqpay/__init__.py
liqpay/liqpay3.py
liqpay/tests/__init__.py
liqpay/tests/test_pay_simple.py
liqpay_sdk_python3-1.0.6.dist-info/METADATA
liqpay_sdk_python3-1.0.6.dist-info/WHEEL
liqpay_sdk_python3-1.0.6.dist-info/top_level.txt
liqpay_sdk_python3-1.0.6.dist-info/RECORD
