Metadata-Version: 2.1
Name: liqpay-sdk-python3
Version: 1.0.6
Summary: LiqPay Python3 SDK
Home-page: https://github.com/aorzh/liqpay-sdk-python3
Requires-Dist: requests
